musicvideos_extras/__init__.py
musicvideos_extras/build.py
musicvideos_extras/build_old.py
musicvideos_extras/tools.py
musicvideos_extras/youtube.py
musicvideos_extras-0.1.2.dist-info/LICENSE
musicvideos_extras-0.1.2.dist-info/METADATA
musicvideos_extras-0.1.2.dist-info/WHEEL
musicvideos_extras-0.1.2.dist-info/top_level.txt
musicvideos_extras-0.1.2.dist-info/RECORD
