Metadata-Version: 2.1
Name: musicvideos-extras
Version: 0.1.2
Summary: Extras for video creation things.
Home-page: UNKNOWN
Author: JustCow
Author-email: <justcow@pm.me>
License: UNKNOWN
Keywords: python,musicvideos,extras,youtube
Platform: UNKNOWN
Classifier: License :: OSI Approved :: GNU General Public License v3 (GPLv3)
Classifier: Programming Language :: Python :: 3
Classifier: Operating System :: Unix
License-File: LICENSE
Requires-Dist: google-api-python-client
Requires-Dist: google-auth-httplib2
Requires-Dist: google-auth-oauthlib
Requires-Dist: moviepy
Requires-Dist: musicvideos
Requires-Dist: oauth2client
Requires-Dist: requests
Requires-Dist: yt-dlp
